LICENSE
MANIFEST.in
README.md
echo_server.py
requirements.txt
setup.py
echo_server.egg-info/PKG-INFO
echo_server.egg-info/SOURCES.txt
echo_server.egg-info/dependency_links.txt
echo_server.egg-info/entry_points.txt
echo_server.egg-info/not-zip-safe
echo_server.egg-info/requires.txt
echo_server.egg-info/top_level.txt